Top module/serial_interface.sv
//Serial module for the Parallel Serial Interface
`timescale 1ns/1ps

`define SOF 8'h5a
`define EOF 8'h0f

module serial_interface
	#(parameter data_width = 5)
	(	input logic 	datain, s_clk, rst_n, req,
		output logic 	dataout, pop);

//==== SIGNALS ====
// input logic s_clk, rst_n;
// the data to be obtained from the FIFO
// input logic datain;

// when the FIFO wants output data (i.e. whenever it is not empty), this signal should be high
// when a frame is finished, the FIFO should set this signal low
// input logic req;

// that data to be sent out of the serial interface
// output logic dataout;

//when there is a successful data sample, this signal is sent high to tell the FIFO to pop the current data
//the serial interface expects new data on the next clock cycle
// output logic pop;

logic nextdataout, inputSample, request;
enum logic [1:0] {IDLE=2'b00, START_T=2'b01, DATA_T=2'b11, END_T=2'b10} state, nextstate;

logic [2:0] delimcounter, nextdelimcounter;
logic [data_width - 1:0] datacounter, nextdatacounter;

//==== FUNCTIONS ====
function findDelim;
  input startDelimeter;
  input [2:0] incount;

  //delimeters are read msb first, so inverted enumeration
  logic [0:7] delimToSend;

  begin: finddelim_def
    if(startDelimeter)
      delimToSend = `SOF;
    else
      delimToSend = `EOF;

    findDelim = delimToSend[incount];
  end: finddelim_def
endfunction: findDelim

//==== ALWAYS BLOCKS ====
always_ff @(posedge s_clk or negedge rst_n)
begin: updateff
  if(rst_n) begin
    state 			<= nextstate;
    delimcounter 	<= nextdelimcounter;
    dataout 		<= nextdataout;
    inputSample 	<= datain;
    request 		<= req;
    datacounter 	<= nextdatacounter;
  end
  else begin
    state 			<= IDLE;
    delimcounter 	<= 0;
    dataout 		<= 0;
    inputSample		<= 0;
    request 		<= 0;
    datacounter 	<= 0;
  end
end: updateff

always_comb
begin: statemachine
  case(state)
    IDLE: begin
      pop = 0;
      nextdatacounter = 0;
      if(request) 
	  begin
        nextstate = START_T;
        nextdelimcounter = 1;
        nextdataout = findDelim(1, delimcounter);
      end
      else
	  begin
        nextstate = IDLE;
        nextdelimcounter = 0;
        nextdataout = 0;
      end
    end

    START_T: begin
      nextdataout = findDelim(1, delimcounter);
      nextdatacounter = 0;
      if(delimcounter < 7) begin
        nextstate = START_T;
        nextdelimcounter = delimcounter + 1;
        if (delimcounter > 4)
          pop = 1;
        else
          pop = 0;
      end
      else begin
        nextstate = DATA_T;
        nextdelimcounter = 0;
        pop = 1;
      end
    end

    DATA_T: begin
      if(datacounter < (2 ** data_width) - 1 ) begin
        nextstate = DATA_T;
        nextdelimcounter = 0;
        nextdataout = inputSample;
        nextdatacounter = datacounter + 1;
        if (datacounter > (2 ** data_width) - 3)
          pop = 0;
        else
          pop = 1;
      end
      else begin
        nextstate = END_T;
        nextdelimcounter = 0;
        nextdataout =  inputSample;
        pop = 0;
        nextdatacounter = 0;
      end
    end

    END_T: begin
      pop = 0;
      nextdatacounter = 0;
      nextdataout = findDelim(0, delimcounter);
      if(delimcounter < 7) begin
        nextdelimcounter = delimcounter + 1;
        nextstate = END_T;
      end
      else begin
        nextdelimcounter = 0;
        nextstate = IDLE;
      end
    end
  endcase
end: statemachine

endmodule //end serial_interface

FIFO/WFSM.sv
module WFSM #(parameter addrbits = 8, depth= 128)
             (output reg                   full,wren,
              output     [addrbits-1:0] wraddr,
              output reg [addrbits  :0] wrptr,
              input      [addrbits  :0] sync_rdptr,
              input insert, flush, clk_in, rst);

reg [1:0] current_state, next_state;
reg  [addrbits:0] wbin;
wire [addrbits:0] wgraynext, wbinnext;
wire full_val;
//States are binary encoded 
localparam RESET = 2'b00, 
           INSERT= 2'b01, 
           IDEAL = 2'b10; 
        

assign wraddr = wbin[addrbits-1:0];
assign wbinnext  = wbin + (insert & ~full);
assign wgraynext = (wbinnext>>1) ^ wbinnext;
assign full_val  = (((wgraynext[addrbits-1]  !=sync_rdptr[addrbits-1]) &&
                   (wgraynext[addrbits-2:0]==sync_rdptr[addrbits-2:0]))||
                   (wbin[addrbits-1:0] >= depth[addrbits-1:0]-1)); 
 
always @(posedge clk_in , negedge rst)
begin
    if(!rst)
     begin
        current_state <= RESET; // non- blocking procedural assignment
        full <= 1'b0;
        wbin <= 0;   
        wrptr <= 0;
        wren <= 0;  
      end    
    else
    begin
        current_state <= next_state;
        case(next_state)
		RESET : begin
			wren <= 0;
            full  <= 0;
            wbin <= 0;  
            wrptr <= 0; 
		    //empty <= 1;
                     end
		INSERT: begin
		    // empty <= 0;
			full <= full_val;
            if(!full_val)
            begin
				wren <= 1;                
                {wbin, wrptr} <= {wbinnext, wgraynext};
            end
            else
            begin
				wren <= 0;
                {wbin, wrptr} <= {wbin, wrptr};
            end
            end
        IDEAL : begin
			wren <= 0;
            full <= full_val;
            end             
        default: begin         
            full  <= 1'b0;
            wbin  <= 0;   
            wrptr <= 0;
            wren <= 0;
            end
        endcase
      end   
end

always@(*)
begin
  next_state = RESET;
  case (current_state)
  RESET : begin
          if (flush)
            next_state = RESET;  // blocking procedural assignment
          else if (insert && !full)     
            next_state = INSERT;
          else
            next_state = IDEAL;   
          end

  INSERT : begin
           if (flush)
              next_state = RESET; 
           else if (insert && !full)
              next_state = INSERT;
           else
              next_state = IDEAL;   
           end

  IDEAL : begin
           if (flush)
              next_state = RESET;  
          else if (insert && !full)
              next_state = INSERT;
          else
              next_state = IDEAL;               
          end
    default: next_state = RESET;  
  endcase 
end

endmodule

Top module/RFSM.sv
module RFSM #(parameter addrbits = 8, depth =128)
             (output reg                empty,rden,
              output     [addrbits-1:0] rdaddr,
              output reg [addrbits  :0] rdptr,
              input      [addrbits  :0] sync_wrptr,
              input remove, clk_out, rst, sync_flush);

reg [1:0] current_state, next_state;
reg  [addrbits:0] rbin;
wire [addrbits:0] rgraynext, rbinnext;
wire empty_val;
//States are binary encoded 
localparam RESET  = 2'b00, 
           REMOVE = 2'b01, 
           IDEAL  = 2'b10; 
        

assign rdaddr = rbin[addrbits-1:0];
assign rbinnext  = rbin + (remove & ~empty);
assign rgraynext = (rbinnext>>1) ^ rbinnext;
assign empty_val = ((rgraynext == sync_wrptr)||(rbin[addrbits-1:0] >= depth[addrbits-1:0]-1));

always @(posedge clk_out , negedge rst)
begin
    if(!rst)
    begin
       current_state <= RESET; // non- blocking procedural assignment
       empty <= 1;
       rbin <= 0;   
       rdptr <= 0;
       rden <= 0;
    end    
    else
    begin
       current_state <= next_state;
       case(next_state)
       RESET : begin
			rden <= 0;
			empty <= 1;
            rbin <= 0;  
            rdptr <= 0;
			end
       REMOVE: begin
			empty <= empty_val;
            if(!empty)
            begin
				rden <= 1;
                {rbin, rdptr} <= {rbinnext, rgraynext};
            end
            else
            begin        
				rden <= 0; 
                {rbin, rdptr} <= {rbin, rdptr};
            end
            end
       IDEAL : begin
            rden <= 0;
			empty <= empty_val;
            {rbin, rdptr} <= {rbin, rdptr};
               end             
       default: begin 
            empty  <= 1;
            rbin   <= 0;   
            rdptr  <= 0;
            rden   <= 0;
             end
        endcase
      end   
end

always@(*)
begin
  next_state = RESET;
  case (current_state)
  RESET : begin
          if (sync_flush)
            next_state = RESET;  // blocking procedural assignment
          else                      
            next_state = IDEAL;          
          end

  REMOVE : begin
           if (sync_flush)
              next_state = RESET;             
           else if (remove && !empty)
               next_state = REMOVE; 
           else
              next_state = IDEAL;    
           end

  IDEAL : begin
           if (sync_flush)
              next_state = RESET;             
          else if (remove && !empty)
              next_state = REMOVE;
          else
              next_state = IDEAL;          
          end

    default: next_state = RESET;
      
  endcase 
end
endmodule

Top module/memory.sv
 module memory #( addrbits=8, depth=128)
               (input clk_in, flush, rst, sync_flush,
                input clk_out, rden, wren, 
                input [addrbits-1:0] rdaddr, wraddr,
                input  dataIn, 
                output reg  dataOut);

reg  FIFO [0:depth-1];
integer i;

// Writing into the FIFO 

always@(posedge clk_in, negedge rst)
begin
    if(!rst)
    begin
		for(i=0;i<depth;i=i+1)
		FIFO[i] <= 0;           
    end
    else if(flush)
    begin
		for(i=0;i<depth;i=i+1)
		FIFO[i] <= 0;
    end           
    else if(wren)        
    begin
		FIFO[wraddr] <= dataIn;
    end
    
end

// Reading from the FIFO 

always@(posedge clk_out, negedge rst)
begin
    if(!rst)
    begin
		dataOut <= FIFO[0];
    end
    else if(sync_flush)
    begin
		dataOut <= FIFO[0];
    end
    else if(rden)
    begin
		dataOut <= FIFO[rdaddr];
    end
    else if(!rden && (rdaddr == 0))
		dataOut <= FIFO[0];
    else if(!rden)
		dataOut <= FIFO[rdaddr];
end
endmodule

Top module/flush_sync.sv
module flush_sync (input clk_in, rst, flush,
                   output reg sync_flush);
            
reg f0;

always @(posedge clk_in , negedge rst) 
	begin
	if(!rst)
	begin
		f0 <= 1'b0;
		sync_flush <= 1'b0;
	end
	else
	begin
		f0 <= flush;
		sync_flush <= f0;
	end
	end
endmodule

Top module/write_sync.sv
module write_sync #(parameter addrbits=8)
            (input clk_in, rst, flush,
             input [addrbits:0] wrptr,
             output reg [addrbits:0] sync_wrptr);
          
reg [addrbits:0] w0;

always @(posedge clk_in , negedge rst) 
	begin
	if(!rst)
	begin
		w0 <= 0;
		sync_wrptr <= 0;
	end
	else if(flush) 
	begin
		w0 <= 0;
		sync_wrptr <= 0;
	end
	else
	begin
		w0 <= wrptr;
		sync_wrptr <= w0;
	end
	end 
endmodule

FIFO/read_sync.sv
module read_sync #(parameter addrbits=8)
                  (input clk_out, rst, sync_flush,
                   input [addrbits:0] rdptr,
                   output reg [addrbits:0] sync_rdptr);

reg [addrbits:0] r0;

always @(posedge clk_out , negedge rst) 
	begin
	if(!rst)
	begin
		r0 <= 0;
		sync_rdptr <= 0;
	end
	else if(sync_flush) 
	begin
		r0 <= 0;
		sync_rdptr <= 0;
	end
	else
	begin
		r0 <= rdptr;
		sync_rdptr <= r0;
	end
	end 
endmodule

FIFO/fifo.sv
`include "read_sync.sv"
`include "write_sync.sv"
`include "flush_sync.sv"
`include "WFSM.sv"
`include "RFSM.sv"
`include "memory.sv"

module fifo #(	parameter	addrbits = 8,
                parameter	depth = 128)
             (	output	dataOut,
				output	full,
				output	empty,
				input	dataIn,
				input	insert, flush, clk_in, rst, 
				input	remove, clk_out);

wire   [addrbits-1:0] wraddr, rdaddr;
wire   [addrbits:0]   wrptr, rdptr, sync_rdptr, sync_wrptr;
wire sync_flush, wren, rden;

read_sync #(addrbits) r2w_uut (.sync_rdptr(sync_rdptr), .rdptr(rdptr),
                               .clk_out(clk_out), .rst(rst), .sync_flush(sync_flush));

write_sync #(addrbits) w2r_uut (.sync_wrptr(sync_wrptr), .wrptr(wrptr),
                                .clk_in(clk_in), .rst(rst), .flush(flush));
                                

flush_sync flush_uut (.sync_flush(sync_flush), .flush(flush),
                                .clk_in(clk_in), .rst(rst));

memory #( addrbits, depth) mem_uut (.dataOut(dataOut), .dataIn(dataIn),
                                             .wraddr(wraddr), .rdaddr(rdaddr),
                                             .rst(rst), .clk_in(clk_in), .flush(flush), 
                                             .clk_out(clk_out), .wren(wren), .rden(rden),
                                             .sync_flush(sync_flush));
                                                                
RFSM #(addrbits, depth) read_uut (.empty(empty), .rdaddr(rdaddr),
                           .rdptr(rdptr), .sync_wrptr(sync_wrptr), 
                           .remove(remove), .clk_out(clk_out),
                           .rst(rst), .sync_flush(sync_flush), .rden(rden));

WFSM  #(addrbits, depth) write_uut (.full(full), .wraddr(wraddr),
                             .wrptr(wrptr), .sync_rdptr(sync_rdptr),
                             .insert(insert), .flush(flush),
                             .clk_in(clk_in), .rst(rst), .wren(wren));


endmodule

Top module/parallel_interface.sv

module parallel_interface (	input p_clk, input n_rst, input	logic req, 
							input	logic [31:0] parallel_data_in,
							output	logic  grant, 
							output	logic serial_data_out,
							output	logic out_data);

  	typedef enum {IDLE, TAKE_INPUT_DATA, SEND_SERIAL_OUTPUT} fsm;
    fsm cs, ns;
  
  	logic grant_temp, serial_data_out_temp;
  	int	  bit_counter_temp, bit_counter;
	logic [31:0] parallel_data_reg, parallel_data_reg_temp;
	logic out_data_temp ;
    //logic out_data = 0; 
  
  	assign serial_data_out = parallel_data_reg[0];
	assign out_data = out_data_temp;
    
	// current_state logic of FSM
	
  always_ff @(posedge p_clk, negedge n_rst) begin
        if(!n_rst) begin
            cs         			<=  IDLE;
            grant				<=	0;
            bit_counter			<= 0;
			parallel_data_reg	<= 0;
			//serial_data_out <= 0;
			//out_data_temp <= 0;
        end
        else begin
            cs          		<= ns;
          	grant				<= grant_temp;
            bit_counter 		<= bit_counter_temp;
            parallel_data_reg 	<= parallel_data_reg_temp;
			//serial_data_out <= serial_data_out_temp;
        end
	end
	
	// next_state and output logic of FSM
	
    always_comb begin
        case(cs)
            IDLE:	begin
              	//serial_data_out_temp = 0;
				bit_counter_temp 		= 0;
				parallel_data_reg_temp 	= 0;
				out_data_temp 			= 0;
              	if(req) begin
                	ns 			= TAKE_INPUT_DATA;
                	grant_temp 	= 1;
              	end
                else begin	
                  	ns 			= IDLE;
                  	grant_temp 	= 0;
                end
            end
          
            TAKE_INPUT_DATA:	begin
              	serial_data_out_temp 	= 0;
              	bit_counter_temp		= 0;
				parallel_data_reg_temp 	= parallel_data_in;
				out_data_temp 			= 1;
            	ns 						= SEND_SERIAL_OUTPUT;
				grant_temp 				= 1;
            end 
          
          SEND_SERIAL_OUTPUT:	begin
              bit_counter_temp 			= bit_counter + 1;         
              parallel_data_reg_temp 	= parallel_data_reg >> 1; 	//Loading the 32-bit parallel input data
              if(bit_counter <= 31 ) 
				ns = cs;
              else begin
                ns 					= IDLE;
				out_data_temp 		= 0;
				bit_counter_temp 	= 0;
				end
            end     
        endcase
    end      
endmodule

Top module/top.sv
`timescale 1ns/1ps
`include "parallel_interface.sv"
`include "fifo.sv"
`include "serial_interface.sv"

module top #( 	parameter datasize = 32,
		parameter addrbits = 8,
		parameter depth = 128)
		(input [datasize-1:0] parallel_data_in,
		input	req,	input	p_clk,	input	n_rst,	input	flush,	input	s_clk,
		output	grant,	output	full,	output	empty,	output	output_psi);
				


wire parallel_to_fifo,fifo_to_serial;
wire insert, pop;

//module instantiation

parallel_interface P1 (	.req(req), .parallel_data_in(parallel_data_in), .p_clk(p_clk), .n_rst(n_rst), 
			.grant(grant), .serial_data_out(parallel_to_fifo), .out_data(insert));

fifo #(addrbits, depth)  F1 (	.dataIn(parallel_to_fifo), .insert(insert), .rst(n_rst),
				.clk_in(p_clk), .flush(flush), .clk_out (s_clk), 
				.full(full), .empty(empty), .dataOut(fifo_to_serial), .remove(pop));

serial_interface S1 (	.datain(fifo_to_serial), .pop(pop), 
			.req(~empty), .s_clk(s_clk), 
			.rst_n(n_rst), .dataout(output_psi));
endmodule

Top module/top_tb.sv
`timescale 10ns/1ns

module top_tb();

wire out, full, empty, grant;
reg  flush, p_clk, rst, s_clk, req;
reg [31:0] parallel_data_in;

top T1( .output_psi(out), .full(full), .empty(empty), .grant(grant),  
	.flush(flush), .s_clk(s_clk), .p_clk(p_clk), .n_rst(rst),
	.req(req), .parallel_data_in(parallel_data_in));

always #2 p_clk = ~ p_clk;
always #4 s_clk = ~ s_clk;
 
initial begin

//$monitor ("datain = %b empty = %b insert = %b output = %b", datain, empty, insert, out);
p_clk = 0;
s_clk = 0;
//datain = 0;
flush = 0;
rst = 0;
#10
rst = 1;
flush = 1;
#40
flush = 0;
#10
req = 1;
#1;
parallel_data_in = 32'h11111111;
#100;
req = 0;
#140
req = 1;
parallel_data_in = 32'hffffffff;
//flush = 1;
//#10
//req = 1;
//#10
//parallel_data_in = 32'hffffffff;
//#80
//req = 0;
	
#500 $finish; 
end
//
/*
    req = 1;
    #1;
    parallel_data_in = 32'h11111111;
    #150;
    req = 0;
*/
//
// initial begin

// $dumpfile("top_vcd.vcd");
// $dumpvars(0, top);
// end

/*always @ (posedge clk_in) begin

	if (insert == 1) begin
		datain = ~ datain;
		//#2;
	end
end */

endmodule

Top module/top_vcd.vcd
$date
	Sun May  2 17:41:43 2021
$end

$version
	Synopsys VCS version I-2014.03-2
$end

$timescale
	1ps
$end

$comment Csum: 1 437aba952df76de7 $end


$scope module top_tb $end

$scope module T1 $end
$var wire 32 ! parallel_data_in [31:0] $end
$var wire 1 " req $end
$var wire 1 # p_clk $end
$var wire 1 $ n_rst $end
$var wire 1 % flush $end
$var wire 1 & s_clk $end
$var wire 1 ' grant $end
$var wire 1 ( full $end
$var wire 1 ) empty $end
$var wire 1 * output_psi $end
$var wire 1 + parallel_to_fifo $end
$var wire 1 , fifo_to_serial $end
$var wire 1 - insert $end
$var wire 1 . pop $end

$scope module P1 $end
$var wire 1 # p_clk $end
$var wire 1 $ n_rst $end
$var reg 1 / req $end
$var reg 32 0 parallel_data_in [31:0] $end
$var reg 1 1 grant $end
$var reg 1 2 serial_data_out $end
$var reg 1 3 out_data $end
$var reg 32 4 cs [31:0] $end
$var reg 32 5 ns [31:0] $end
$var reg 1 6 grant_temp $end
$var reg 1 7 serial_data_out_temp $end
$var reg 32 8 bit_counter_temp [31:0] $end
$var reg 32 9 bit_counter [31:0] $end
$var reg 32 : parallel_data_reg [31:0] $end
$var reg 32 ; parallel_data_reg_temp [31:0] $end
$var reg 1 < out_data_temp $end
$upscope $end


$scope module F1 $end
$var wire 1 , dataOut $end
$var wire 1 ( full $end
$var wire 1 ) empty $end
$var wire 1 + dataIn $end
$var wire 1 - insert $end
$var wire 1 % flush $end
$var wire 1 # clk_in $end
$var wire 1 $ rst $end
$var wire 1 . remove $end
$var wire 1 & clk_out $end
$var wire 8 = wraddr [7:0] $end
$var wire 8 > rdaddr [7:0] $end
$var wire 9 ? wrptr [8:0] $end
$var wire 9 @ rdptr [8:0] $end
$var wire 9 A sync_rdptr [8:0] $end
$var wire 9 B sync_wrptr [8:0] $end
$var wire 1 C sync_flush $end
$var wire 1 D wren $end
$var wire 1 E rden $end

$scope module r2w_uut $end
$var wire 1 & clk_out $end
$var wire 1 $ rst $end
$var wire 1 C sync_flush $end
$var wire 9 @ rdptr [8:0] $end
$var reg 9 F sync_rdptr [8:0] $end
$var reg 9 G r0 [8:0] $end
$upscope $end


$scope module w2r_uut $end
$var wire 1 # clk_in $end
$var wire 1 $ rst $end
$var wire 1 % flush $end
$var wire 9 ? wrptr [8:0] $end
$var reg 9 H sync_wrptr [8:0] $end
$var reg 9 I w0 [8:0] $end
$upscope $end


$scope module flush_uut $end
$var wire 1 # clk_in $end
$var wire 1 $ rst $end
$var wire 1 % flush $end
$var reg 1 J sync_flush $end
$var reg 1 K f0 $end
$upscope $end


$scope module mem_uut $end
$var wire 1 # clk_in $end
$var wire 1 % flush $end
$var wire 1 $ rst $end
$var wire 1 C sync_flush $end
$var wire 1 & clk_out $end
$var wire 1 E rden $end
$var wire 1 D wren $end
$var wire 8 > rdaddr [7:0] $end
$var wire 8 = wraddr [7:0] $end
$var wire 1 + dataIn $end
$var reg 1 L dataOut $end
$var integer 32 M i $end
$upscope $end


$scope module read_uut $end
$var reg 1 N empty $end
$var reg 1 O rden $end
$var wire 8 > rdaddr [7:0] $end
$var reg 9 P rdptr [8:0] $end
$var wire 9 B sync_wrptr [8:0] $end
$var wire 1 . remove $end
$var wire 1 & clk_out $end
$var wire 1 $ rst $end
$var wire 1 C sync_flush $end
$var reg 2 Q current_state [1:0] $end
$var reg 2 R next_state [1:0] $end
$var reg 9 S rbin [8:0] $end
$var wire 9 T rgraynext [8:0] $end
$var wire 9 U rbinnext [8:0] $end
$var wire 1 V empty_val $end
$upscope $end


$scope module write_uut $end
$var reg 1 W full $end
$var reg 1 X wren $end
$var wire 8 = wraddr [7:0] $end
$var reg 9 Y wrptr [8:0] $end
$var wire 9 A sync_rdptr [8:0] $end
$var wire 1 - insert $end
$var wire 1 % flush $end
$var wire 1 # clk_in $end
$var wire 1 $ rst $end
$var reg 2 Z current_state [1:0] $end
$var reg 2 [ next_state [1:0] $end
$var reg 9 \ wbin [8:0] $end
$var wire 9 ] wgraynext [8:0] $end
$var wire 9 ^ wbinnext [8:0] $end
$var wire 1 _ full_val $end
$upscope $end

$upscope $end


$scope module S1 $end
$var reg 1 ` datain $end
$var reg 1 a s_clk $end
$var reg 1 b rst_n $end
$var reg 1 c req $end
$var reg 1 d dataout $end
$var reg 1 e pop $end
$var reg 1 f nextdataout $end
$var reg 1 g inputSample $end
$var reg 1 h request $end
$var reg 2 i state [1:0] $end
$var reg 2 j nextstate [1:0] $end
$var reg 3 k delimcounter [2:0] $end
$var reg 3 l nextdelimcounter [2:0] $end
$var reg 5 m datacounter [4:0] $end
$var reg 5 n nextdatacounter [4:0] $end

$scope function findDelim $end
$var reg 1 o findDelim $end
$var reg 1 p startDelimeter $end
$var reg 3 q incount [2:0] $end
$var reg 8 r delimToSend [0:7] $end

$scope begin finddelim_def $end
$upscope $end

$upscope $end


$scope begin updateff $end
$upscope $end


$scope begin statemachine $end
$upscope $end

$upscope $end

$upscope $end

$upscope $end

$enddefinitions $end

#0
$dumpvars
01
x/
0e
0c
x`
0d
1V
0K
x,
xo
xp
0J
0_
06
0g
0-
xL
0f
03
0<
0+
0.
0E
1N
0O
0h
02
x7
0C
0D
0W
0X
bxxxxxxxxxxxxxxxxxxxxxxxxxxxxxxxx 0
b00 Q
b00000 m
b000 k
bxxxxxxxx r
bxxx q
b00000000000000000000000010000000 M
b10 R
b00000 n
b000 l
b00 j
b00000000000000000000000000000000 :
b00000000000000000000000000000000 ;
b000000000 G
b000000000 F
b000000000 S
b000000000 U
b00000000 >
b000000000 @
b000000000 P
b000000000 T
b00 i
b000000000 A
b000000000 B
b000000000 I
b000000000 H
b000000000 \
b000000000 ^
b000000000 ]
b00000000 =
b00 Z
b10 [
b000000000 Y
b000000000 ?
b00000000000000000000000000000000 9
b00000000000000000000000000000000 8
b00000000000000000000000000000000 4
b00000000000000000000000000000000 5
0%
0&
0#
0$
x"
bxxxxxxxxxxxxxxxxxxxxxxxxxxxxxxxx !
0*
0(
1)
0'
0a
0b
$end
#20000
1#
#40000
1&
1a
0#
0L
0,
0`
#60000
1#
#80000
0&
0a
0#
#100000
1$
1b
1%
1#
b00 [
1K
#120000
1&
1a
0#
b10 Q
#140000
1#
1J
1C
b00 R
#160000
0&
0a
0#
#180000
1#
#200000
1&
1a
0#
b00 Q
#220000
1#
#240000
0&
0a
0#
#260000
1#
#280000
1&
1a
0#
#300000
1#
#320000
0&
0a
0#
#340000
1#
#360000
1&
1a
0#
#380000
1#
#400000
0&
0a
0#
#420000
1#
#440000
1&
1a
0#
#460000
1#
#480000
0&
0a
0#
#500000
0%
1#
b10 [
0K
b10 Z
#520000
1&
1a
0#
#540000
1#
0J
0C
b10 R
#560000
0&
0a
0#
#580000
1#
#600000
1"
1/
1&
1a
0#
16
b00000000000000000000000000000001 5
b10 Q
#610000
b00010001000100010001000100010001 !
b00010001000100010001000100010001 0
#620000
1#
b00000000000000000000000000000001 4
11
1'
b00000000000000000000000000000010 5
1<
1-
13
b00010001000100010001000100010001 ;
07
b000000001 ^
b000000001 ]
b01 [
#640000
0&
0a
0#
#660000
1#
b00000000000000000000000000000010 4
b00010001000100010001000100010001 :
12
1+
b01 Z
1X
1D
b000000001 \
b00000001 =
b000000001 Y
b000000001 ?
b00001000100010001000100010001000 ;
b00000000000000000000000000000001 8
b000000010 ^
b000000011 ]
#680000
1&
1a
0#
#700000
1#
b000000001 I
b00000000000000000000000000000001 9
b00001000100010001000100010001000 :
02
0+
b000000010 \
b00000010 =
b000000011 Y
b000000011 ?
b00000100010001000100010001000100 ;
b00000000000000000000000000000010 8
b000000011 ^
b000000010 ]
#720000
0&
0a
0#
#740000
1#
b000000011 I
b000000001 H
b000000001 B
b00000000000000000000000000000010 9
b00000100010001000100010001000100 :
b000000011 \
b00000011 =
b000000010 Y
b000000010 ?
0V
b00000010001000100010001000100010 ;
b00000000000000000000000000000011 8
b000000100 ^
b000000110 ]
#760000
1&
1a
0#
0N
0)
1c
#780000
1#
b000000010 I
b000000011 H
b000000011 B
b00000000000000000000000000000011 9
b00000010001000100010001000100010 :
b000000100 \
b00000100 =
b000000110 Y
b000000110 ?
b00000001000100010001000100010001 ;
b00000000000000000000000000000100 8
b000000101 ^
b000000111 ]
#800000
0&
0a
0#
#820000
1#
b000000110 I
b000000010 H
b000000010 B
b00000000000000000000000000000100 9
b00000001000100010001000100010001 :
12
1+
b000000101 \
b00000101 =
b000000111 Y
b000000111 ?
b00000000100010001000100010001000 ;
b00000000000000000000000000000101 8
b000000110 ^
b000000101 ]
#840000
1&
1a
0#
1h
b001 l
b01 j
0o
b01011010 r
b000 q
1p
#860000
1#
b000000111 I
b000000110 H
b000000110 B
b00000000000000000000000000000101 9
b00000000100010001000100010001000 :
02
0+
b000000110 \
b00000110 =
b000000101 Y
b000000101 ?
b00000000010001000100010001000100 ;
b00000000000000000000000000000110 8
b000000111 ^
b000000100 ]
#880000
0&
0a
0#
#900000
1#
b000000101 I
b000000111 H
b000000111 B
b00000000000000000000000000000110 9
b00000000010001000100010001000100 :
b000000111 \
b00000111 =
b000000100 Y
b000000100 ?
b00000000001000100010001000100010 ;
b00000000000000000000000000000111 8
b000001000 ^
b000001100 ]
#920000
1&
1a
0#
b01 i
b001 k
1f
b010 l
1o
b001 q
#940000
1#
b000000100 I
b000000101 H
b000000101 B
b00000000000000000000000000000111 9
b00000000001000100010001000100010 :
b000001000 \
b00001000 =
b000001100 Y
b000001100 ?
b00000000000100010001000100010001 ;
b00000000000000000000000000001000 8
b000001001 ^
b000001101 ]
#960000
0&
0a
0#
#980000
1#
b000001100 I
b000000100 H
b000000100 B
b00000000000000000000000000001000 9
b00000000000100010001000100010001 :
12
1+
b000001001 \
b00001001 =
b000001101 Y
b000001101 ?
b00000000000010001000100010001000 ;
b00000000000000000000000000001001 8
b000001010 ^
b000001111 ]
#1000000
1&
1a
0#
b010 k
1d
1*
0f
b011 l
0o
b010 q
#1020000
1#
b000001101 I
b000001100 H
b000001100 B
b00000000000000000000000000001001 9
b00000000000010001000100010001000 :
02
0+
b000001010 \
b00001010 =
b000001111 Y
b000001111 ?
b00000000000001000100010001000100 ;
b00000000000000000000000000001010 8
b000001011 ^
b000001110 ]
#1040000
0&
0a
0#
#1060000
1#
b000001111 I
b000001101 H
b000001101 B
b00000000000000000000000000001010 9
b00000000000001000100010001000100 :
b000001011 \
b00001011 =
b000001110 Y
b000001110 ?
b00000000000000100010001000100010 ;
b00000000000000000000000000001011 8
b000001100 ^
b000001010 ]
#1080000
1&
1a
0#
b011 k
0d
0*
1f
b100 l
1o
b011 q
#1100000
1#
b000001110 I
b000001111 H
b000001111 B
b00000000000000000000000000001011 9
b00000000000000100010001000100010 :
b000001100 \
b00001100 =
b000001010 Y
b000001010 ?
b00000000000000010001000100010001 ;
b00000000000000000000000000001100 8
b000001101 ^
b000001011 ]
#1120000
0&
0a
0#
#1140000
1#
b000001010 I
b000001110 H
b000001110 B
b00000000000000000000000000001100 9
b00000000000000010001000100010001 :
12
1+
b000001101 \
b00001101 =
b000001011 Y
b000001011 ?
b00000000000000001000100010001000 ;
b00000000000000000000000000001101 8
b000001110 ^
b000001001 ]
#1160000
1&
1a
0#
b100 k
1d
1*
b101 l
b100 q
#1180000
1#
b000001011 I
b000001010 H
b000001010 B
b00000000000000000000000000001101 9
b00000000000000001000100010001000 :
02
0+
b000001110 \
b00001110 =
b000001001 Y
b000001001 ?
b00000000000000000100010001000100 ;
b00000000000000000000000000001110 8
b000001111 ^
b000001000 ]
#1200000
0&
0a
0#
#1220000
1#
b000001001 I
b000001011 H
b000001011 B
b00000000000000000000000000001110 9
b00000000000000000100010001000100 :
b000001111 \
b00001111 =
b000001000 Y
b000001000 ?
b00000000000000000010001000100010 ;
b00000000000000000000000000001111 8
b000010000 ^
b000011000 ]
#1240000
1&
1a
0#
b101 k
0f
b110 l
1e
1.
0o
b101 q
b01 R
b000000001 U
b000000001 T
#1260000
1#
b000001000 I
b000001001 H
b000001001 B
b00000000000000000000000000001111 9
b00000000000000000010001000100010 :
b000010000 \
b00010000 =
b000011000 Y
b000011000 ?
b00000000000000000001000100010001 ;
b00000000000000000000000000010000 8
b000010001 ^
b000011001 ]
#1280000
0&
0a
0#
#1300000
1#
b000011000 I
b000001000 H
b000001000 B
b00000000000000000000000000010000 9
b00000000000000000001000100010001 :
12
1+
b000010001 \
b00010001 =
b000011001 Y
b000011001 ?
b00000000000000000000100010001000 ;
b00000000000000000000000000010001 8
b000010010 ^
b000011011 ]
#1320000
1&
1a
0#
b01 Q
1O
1E
b000000001 S
b00000001 >
b000000001 P
b000000001 @
b110 k
0d
0*
b000000010 U
b000000010 T
b000000011 T
1f
b111 l
1o
b110 q
#1340000
1#
b000011001 I
b000011000 H
b000011000 B
b00000000000000000000000000010001 9
b00000000000000000000100010001000 :
02
0+
b000010010 \
b00010010 =
b000011011 Y
b000011011 ?
b00000000000000000000010001000100 ;
b00000000000000000000000000010010 8
b000010011 ^
b000011010 ]
#1360000
0&
0a
0#
#1380000
1#
b000011011 I
b000011001 H
b000011001 B
b00000000000000000000000000010010 9
b00000000000000000000010001000100 :
b000010011 \
b00010011 =
b000011010 Y
b000011010 ?
b00000000000000000000001000100010 ;
b00000000000000000000000000010011 8
b000010100 ^
b000011110 ]
#1400000
1&
1a
0#
b000000001 G
1L
1,
1`
b000000010 S
b00000010 >
b000000011 P
b000000011 @
b111 k
1d
1*
b000000011 U
b000000010 T
0f
b000 l
b11 j
0o
b111 q
#1420000
1#
b000011010 I
b000011011 H
b000011011 B
b00000000000000000000000000010011 9
b00000000000000000000001000100010 :
b000010100 \
b00010100 =
b000011110 Y
b000011110 ?
b00000000000000000000000100010001 ;
b00000000000000000000000000010100 8
b000010101 ^
b000011111 ]
#1440000
0&
0a
0#
