FIFO/WFSM.sv
module WFSM #(parameter addrbits = 8, depth= 128)
             (output reg                   full,wren,
              output     [addrbits-1:0] wraddr,
              output reg [addrbits  :0] wrptr,
              input      [addrbits  :0] sync_rdptr,
              input insert, flush, clk_in, rst);

reg [1:0] current_state, next_state;
reg  [addrbits:0] wbin;
wire [addrbits:0] wgraynext, wbinnext;
wire full_val;
//States are binary encoded 
localparam RESET = 2'b00, 
           INSERT= 2'b01, 
           IDEAL = 2'b10; 
        

assign wraddr = wbin[addrbits-1:0];
assign wbinnext  = wbin + (insert & ~full);
assign wgraynext = (wbinnext>>1) ^ wbinnext;
assign full_val  = (((wgraynext[addrbits-1]  !=sync_rdptr[addrbits-1]) &&
                   (wgraynext[addrbits-2:0]==sync_rdptr[addrbits-2:0]))||
                   (wbin[addrbits-1:0] >= depth[addrbits-1:0]-1)); 
 
always @(posedge clk_in , negedge rst)
begin
    if(!rst)
     begin
        current_state <= RESET; // non- blocking procedural assignment
        full <= 1'b0;
        wbin <= 0;   
        wrptr <= 0;
        wren <= 0;  
      end    
    else
    begin
        current_state <= next_state;
        case(next_state)
		RESET : begin
			wren <= 0;
            full  <= 0;
            wbin <= 0;  
            wrptr <= 0; 
		    //empty <= 1;
                     end
		INSERT: begin
		    // empty <= 0;
			full <= full_val;
            if(!full_val)
            begin
				wren <= 1;                
                {wbin, wrptr} <= {wbinnext, wgraynext};
            end
            else
            begin
				wren <= 0;
                {wbin, wrptr} <= {wbin, wrptr};
            end
            end
        IDEAL : begin
			wren <= 0;
            full <= full_val;
            end             
        default: begin         
            full  <= 1'b0;
            wbin  <= 0;   
            wrptr <= 0;
            wren <= 0;
            end
        endcase
      end   
end

always@(*)
begin
  next_state = RESET;
  case (current_state)
  RESET : begin
          if (flush)
            next_state = RESET;  // blocking procedural assignment
          else if (insert && !full)     
            next_state = INSERT;
          else
            next_state = IDEAL;   
          end

  INSERT : begin
           if (flush)
              next_state = RESET; 
           else if (insert && !full)
              next_state = INSERT;
           else
              next_state = IDEAL;   
           end

  IDEAL : begin
           if (flush)
              next_state = RESET;  
          else if (insert && !full)
              next_state = INSERT;
          else
              next_state = IDEAL;               
          end
    default: next_state = RESET;  
  endcase 
end

endmodule

Top module/RFSM.sv
module RFSM #(parameter addrbits = 8, depth =128)
             (output reg                empty,rden,
              output     [addrbits-1:0] rdaddr,
              output reg [addrbits  :0] rdptr,
              input      [addrbits  :0] sync_wrptr,
              input remove, clk_out, rst, sync_flush);

reg [1:0] current_state, next_state;
reg  [addrbits:0] rbin;
wire [addrbits:0] rgraynext, rbinnext;
wire empty_val;
//States are binary encoded 
localparam RESET  = 2'b00, 
           REMOVE = 2'b01, 
           IDEAL  = 2'b10; 
        

assign rdaddr = rbin[addrbits-1:0];
assign rbinnext  = rbin + (remove & ~empty);
assign rgraynext = (rbinnext>>1) ^ rbinnext;
assign empty_val = ((rgraynext == sync_wrptr)||(rbin[addrbits-1:0] >= depth[addrbits-1:0]-1));

always @(posedge clk_out , negedge rst)
begin
    if(!rst)
    begin
       current_state <= RESET; // non- blocking procedural assignment
       empty <= 1;
       rbin <= 0;   
       rdptr <= 0;
       rden <= 0;
    end    
    else
    begin
       current_state <= next_state;
       case(next_state)
       RESET : begin
			rden <= 0;
			empty <= 1;
            rbin <= 0;  
            rdptr <= 0;
			end
       REMOVE: begin
			empty <= empty_val;
            if(!empty)
            begin
				rden <= 1;
                {rbin, rdptr} <= {rbinnext, rgraynext};
            end
            else
            begin        
				rden <= 0; 
                {rbin, rdptr} <= {rbin, rdptr};
            end
            end
       IDEAL : begin
            rden <= 0;
			empty <= empty_val;
            {rbin, rdptr} <= {rbin, rdptr};
               end             
       default: begin 
            empty  <= 1;
            rbin   <= 0;   
            rdptr  <= 0;
            rden   <= 0;
             end
        endcase
      end   
end

always@(*)
begin
  next_state = RESET;
  case (current_state)
  RESET : begin
          if (sync_flush)
            next_state = RESET;  // blocking procedural assignment
          else                      
            next_state = IDEAL;          
          end

  REMOVE : begin
           if (sync_flush)
              next_state = RESET;             
           else if (remove && !empty)
               next_state = REMOVE; 
           else
              next_state = IDEAL;    
           end

  IDEAL : begin
           if (sync_flush)
              next_state = RESET;             
          else if (remove && !empty)
              next_state = REMOVE;
          else
              next_state = IDEAL;          
          end

    default: next_state = RESET;
      
  endcase 
end
endmodule

Top module/memory.sv
 module memory #( addrbits=8, depth=128)
               (input clk_in, flush, rst, sync_flush,
                input clk_out, rden, wren, 
                input [addrbits-1:0] rdaddr, wraddr,
                input  dataIn, 
                output reg  dataOut);

reg  FIFO [0:depth-1];
integer i;

// Writing into the FIFO 

always@(posedge clk_in, negedge rst)
begin
    if(!rst)
    begin
		for(i=0;i<depth;i=i+1)
		FIFO[i] <= 0;           
    end
    else if(flush)
    begin
		for(i=0;i<depth;i=i+1)
		FIFO[i] <= 0;
    end           
    else if(wren)        
    begin
		FIFO[wraddr] <= dataIn;
    end
    
end

// Reading from the FIFO 

always@(posedge clk_out, negedge rst)
begin
    if(!rst)
    begin
		dataOut <= FIFO[0];
    end
    else if(sync_flush)
    begin
		dataOut <= FIFO[0];
    end
    else if(rden)
    begin
		dataOut <= FIFO[rdaddr];
    end
    else if(!rden && (rdaddr == 0))
		dataOut <= FIFO[0];
    else if(!rden)
		dataOut <= FIFO[rdaddr];
end
endmodule

Top module/flush_sync.sv
module flush_sync (input clk_in, rst, flush,
                   output reg sync_flush);
            
reg f0;

always @(posedge clk_in , negedge rst) 
	begin
	if(!rst)
	begin
		f0 <= 1'b0;
		sync_flush <= 1'b0;
	end
	else
	begin
		f0 <= flush;
		sync_flush <= f0;
	end
	end
endmodule

Top module/write_sync.sv
module write_sync #(parameter addrbits=8)
            (input clk_in, rst, flush,
             input [addrbits:0] wrptr,
             output reg [addrbits:0] sync_wrptr);
          
reg [addrbits:0] w0;

always @(posedge clk_in , negedge rst) 
	begin
	if(!rst)
	begin
		w0 <= 0;
		sync_wrptr <= 0;
	end
	else if(flush) 
	begin
		w0 <= 0;
		sync_wrptr <= 0;
	end
	else
	begin
		w0 <= wrptr;
		sync_wrptr <= w0;
	end
	end 
endmodule

FIFO/read_sync.sv
module read_sync #(parameter addrbits=8)
                  (input clk_out, rst, sync_flush,
                   input [addrbits:0] rdptr,
                   output reg [addrbits:0] sync_rdptr);

reg [addrbits:0] r0;

always @(posedge clk_out , negedge rst) 
	begin
	if(!rst)
	begin
		r0 <= 0;
		sync_rdptr <= 0;
	end
	else if(sync_flush) 
	begin
		r0 <= 0;
		sync_rdptr <= 0;
	end
	else
	begin
		r0 <= rdptr;
		sync_rdptr <= r0;
	end
	end 
endmodule

FIFO/fifo.sv
`include "read_sync.sv"
`include "write_sync.sv"
`include "flush_sync.sv"
`include "WFSM.sv"
`include "RFSM.sv"
`include "memory.sv"

module fifo #(	parameter	addrbits = 8,
                parameter	depth = 128)
             (	output	dataOut,
				output	full,
				output	empty,
				input	dataIn,
				input	insert, flush, clk_in, rst, 
				input	remove, clk_out);

wire   [addrbits-1:0] wraddr, rdaddr;
wire   [addrbits:0]   wrptr, rdptr, sync_rdptr, sync_wrptr;
wire sync_flush, wren, rden;

read_sync #(addrbits) r2w_uut (.sync_rdptr(sync_rdptr), .rdptr(rdptr),
                               .clk_out(clk_out), .rst(rst), .sync_flush(sync_flush));

write_sync #(addrbits) w2r_uut (.sync_wrptr(sync_wrptr), .wrptr(wrptr),
                                .clk_in(clk_in), .rst(rst), .flush(flush));
                                

flush_sync flush_uut (.sync_flush(sync_flush), .flush(flush),
                                .clk_in(clk_in), .rst(rst));

memory #( addrbits, depth) mem_uut (.dataOut(dataOut), .dataIn(dataIn),
                                             .wraddr(wraddr), .rdaddr(rdaddr),
                                             .rst(rst), .clk_in(clk_in), .flush(flush), 
                                             .clk_out(clk_out), .wren(wren), .rden(rden),
                                             .sync_flush(sync_flush));
                                                                
RFSM #(addrbits, depth) read_uut (.empty(empty), .rdaddr(rdaddr),
                           .rdptr(rdptr), .sync_wrptr(sync_wrptr), 
                           .remove(remove), .clk_out(clk_out),
                           .rst(rst), .sync_flush(sync_flush), .rden(rden));

WFSM  #(addrbits, depth) write_uut (.full(full), .wraddr(wraddr),
                             .wrptr(wrptr), .sync_rdptr(sync_rdptr),
                             .insert(insert), .flush(flush),
                             .clk_in(clk_in), .rst(rst), .wren(wren));


endmodule

FIFO/fifo_tb.sv
//`include "fifo.sv"
module fifo_tb();

//parameter datasize = 32;
parameter addrbits = 8;
parameter depth = 128;
wire dataOut;
wire full, empty;
reg  dataIn;
reg insert, flush, clk_in, rst; 
reg remove, clk_out;
//------------------- For random vector genration ------------
integer ft; // integer used for flush time
integer rt; // integer used for reset time
integer f,r; // integer to use in for loop
integer dataIn_time, in_rm_time;
integer clk_in_period; //ns clk_in period
integer clk_out_period; //ns clk_out period 

fifo #( addrbits, depth) topuut (.dataOut(dataOut), .dataIn(dataIn),
                                 .clk_out (clk_out), .full(full),
                                 .empty(empty), .clk_in(clk_in),
                                 .insert(insert), .flush(flush), 
								 .remove(remove), .rst(rst));

initial
begin
	rst = 1'b0;
	dataIn = 32'h0;
	insert = 1'b0;
	remove = 1'b0;
	flush = 1'b0;
	dataIn_time = 2'b10; // data input time
	in_rm_time = 10;  // insert remove wait time
	clk_in_period = 1'b1;
	clk_out_period =2'b10;

	#10;  //global wait for reset
	//------ corner cases---------//
	//rst = 1'b1;
	//    insert = 1'b1;      //-----\   
	//    #400 insert = 1'b0; //------\  To check corner cases 
	//    remove = 1'b1;      //------/  
	//    #530 remove = 1'b0; //-----/
	rst=1'b0;
	#2 rst=1'b1;
	#10 flush=1'b1;
	#2 flush=1'b0;
	#40 flush=1'b0;
	#20 rst=1'b1;
	insert = 1'b1;
	#50 insert = 1'b0;
	#10 remove = 1'b1;
	#100
	remove = 1'b0;
	flush=1'b1;
	#2 rst=1'b1;
	flush=1'b0;
end

initial
begin
    clk_in = 0;
    forever #1 clk_in = ~clk_in;
end

initial
begin
    clk_out = 0;
    forever #2 clk_out = ~clk_out;
end
/*
initial
begin
#980;   // wait for corner cases test to finish
	forever
	 begin
		#(in_rm_time) insert={$random}%2; //Modulus to get 0 and 1 from random number 
		in_rm_time = in_rm_time + 5;
		remove = ~insert;
	 end
    end
*/
initial
  begin
    #1;
    forever
    begin  // random number
    #(dataIn_time) dataIn=$random;
    end
  end

/*initial
	begin
        #980 // wait for corner cases test to finish
		for(r=1;r<3;r=r+1) // 2 times reset random logic
		begin
		rt={$random}%1000;//Modulus to get number below 1000 from random number 
		#rt rst = 1'b0;
		#5 rst = 1'b1;
		end
	end
*/
/*initial
	begin
     #980 // wait for corner cases test to finish
	 for(f=1;f<5;f=f+1) // 4 times flush random logic
		begin
		ft={$random}%1500;//Modulus to get number below 1500 from random number
		#ft flush = 1'b1;
		#15 flush = 1'b0;
		end
	end
*/
//-------------------- display wth random vectors ----------------
// initial
// begin
// $display("\n------------- Simulation Result with Random Vectors----------- \n\n");
// $monitor("%04t  rst=%b  clk_in=%b  dataIn=%h  insert=%b  clk_out=%b  remove=%b  flush=%b  dataOut=%h  empty=%b  full= %b \n----------------------\t--------------------------\t----------------------\t---------------\t------------------", 
          // $time, rst, clk_in, dataIn, insert, clk_out, remove, topuut.flush, dataOut, topuut.empty, topuut.full);  
          

// end

initial
begin
$dumpfile("fifo_vcd.vcd");
$dumpvars(); 
end

initial
begin
#300 $finish;
end
endmodule

FIFO/fifo_vcd.vcd
$date
	Sun May  2 11:24:15 2021
$end

$version
	Synopsys VCS version I-2014.03-2
$end

$timescale
	1s
$end

$comment Csum: 1 1610d8697bd18ef5 $end


$scope module fifo_tb $end
$var wire 1 ! dataOut $end
$var wire 1 " full $end
$var wire 1 # empty $end
$var reg 1 $ dataIn $end
$var reg 1 % insert $end
$var reg 1 & flush $end
$var reg 1 ' clk_in $end
$var reg 1 ( rst $end
$var reg 1 ) remove $end
$var reg 1 * clk_out $end
$var integer 32 + ft $end
$var integer 32 , rt $end
$var integer 32 - f $end
$var integer 32 . r $end
$var integer 32 / dataIn_time $end
$var integer 32 0 in_rm_time $end
$var integer 32 1 clk_in_period $end
$var integer 32 2 clk_out_period $end

$scope module topuut $end
$var wire 1 ! dataOut $end
$var wire 1 " full $end
$var wire 1 # empty $end
$var wire 1 $ dataIn $end
$var wire 1 % insert $end
$var wire 1 & flush $end
$var wire 1 ' clk_in $end
$var wire 1 ( rst $end
$var wire 1 ) remove $end
$var wire 1 * clk_out $end
$var wire 8 3 wraddr [7:0] $end
$var wire 8 4 rdaddr [7:0] $end
$var wire 9 5 wrptr [8:0] $end
$var wire 9 6 rdptr [8:0] $end
$var wire 9 7 sync_rdptr [8:0] $end
$var wire 9 8 sync_wrptr [8:0] $end
$var wire 1 9 sync_flush $end
$var wire 1 : wren $end
$var wire 1 ; rden $end

$scope module r2w_uut $end
$var wire 1 * clk_out $end
$var wire 1 ( rst $end
$var wire 1 9 sync_flush $end
$var wire 9 6 rdptr [8:0] $end
$var reg 9 < sync_rdptr [8:0] $end
$var reg 9 = r0 [8:0] $end
$upscope $end


$scope module w2r_uut $end
$var wire 1 ' clk_in $end
$var wire 1 ( rst $end
$var wire 1 & flush $end
$var wire 9 5 wrptr [8:0] $end
$var reg 9 > sync_wrptr [8:0] $end
$var reg 9 ? w0 [8:0] $end
$upscope $end


$scope module flush_uut $end
$var wire 1 ' clk_in $end
$var wire 1 ( rst $end
$var wire 1 & flush $end
$var reg 1 @ sync_flush $end
$var reg 1 A f0 $end
$upscope $end


$scope module mem_uut $end
$var wire 1 ' clk_in $end
$var wire 1 & flush $end
$var wire 1 ( rst $end
$var wire 1 9 sync_flush $end
$var wire 1 * clk_out $end
$var wire 1 ; rden $end
$var wire 1 : wren $end
$var wire 8 4 rdaddr [7:0] $end
$var wire 8 3 wraddr [7:0] $end
$var wire 1 $ dataIn $end
$var reg 1 ! dataOut $end
$var integer 32 B i $end
$upscope $end


$scope module read_uut $end
$var reg 1 # empty $end
$var reg 1 C rden $end
$var wire 8 4 rdaddr [7:0] $end
$var reg 9 D rdptr [8:0] $end
$var wire 9 8 sync_wrptr [8:0] $end
$var wire 1 ) remove $end
$var wire 1 * clk_out $end
$var wire 1 ( rst $end
$var wire 1 9 sync_flush $end
$var reg 2 E current_state [1:0] $end
$var reg 2 F next_state [1:0] $end
$var reg 9 G rbin [8:0] $end
$var wire 9 H rgraynext [8:0] $end
$var wire 9 I rbinnext [8:0] $end
$var wire 1 J empty_val $end
$upscope $end


$scope module write_uut $end
$var reg 1 " full $end
$var reg 1 K wren $end
$var wire 8 3 wraddr [7:0] $end
$var reg 9 L wrptr [8:0] $end
$var wire 9 7 sync_rdptr [8:0] $end
$var wire 1 % insert $end
$var wire 1 & flush $end
$var wire 1 ' clk_in $end
$var wire 1 ( rst $end
$var reg 2 M current_state [1:0] $end
$var reg 2 N next_state [1:0] $end
$var reg 9 O wbin [8:0] $end
$var wire 9 P wgraynext [8:0] $end
$var wire 9 Q wbinnext [8:0] $end
$var wire 1 R full_val $end
$upscope $end

$upscope $end

$upscope $end

$enddefinitions $end

#0
$dumpvars
0'
0*
0$
1J
0A
0&
0@
0R
0%
x!
0;
1#
0C
0)
0(
09
0:
0"
0K
b00000000000000000000000000000001 1
b00000000000000000000000000000010 2
b00 E
b00000000000000000000000000000010 /
bxxxxxxxxxxxxxxxxxxxxxxxxxxxxxxxx -
bxxxxxxxxxxxxxxxxxxxxxxxxxxxxxxxx +
b00000000000000000000000010000000 B
b00000000000000000000000000001010 0
b10 F
bxxxxxxxxxxxxxxxxxxxxxxxxxxxxxxxx .
b000000000 =
b000000000 <
b000000000 G
b000000000 I
b00000000 4
b000000000 6
b000000000 D
b000000000 H
bxxxxxxxxxxxxxxxxxxxxxxxxxxxxxxxx ,
b000000000 7
b000000000 8
b000000000 ?
b000000000 >
b000000000 O
b000000000 Q
b000000000 P
b00000000 3
b00 M
b10 N
b000000000 L
b000000000 5
$end
#1
1'
#2
1*
0'
0!
#3
1'
#4
0*
0'
#5
1$
1'
#6
1*
0'
#7
1'
#8
0*
0'
#9
1'
#10
1*
0'
#11
1'
#12
1(
0*
0'
#13
1'
b10 M
#14
1*
0'
b10 E
#15
1'
#16
0*
0'
#17
0$
1'
#18
1*
0'
#19
1$
1'
#20
0*
0'
#21
1'
#22
1&
1*
0'
b00 N
#23
0$
1'
1A
b00 M
#24
0&
0*
0'
b10 N
#25
1$
1'
0A
1@
19
b10 M
b00 F
#26
1*
0'
b00 E
#27
1'
0@
09
b10 F
#28
0*
0'
#29
0$
1'
#30
1*
0'
b10 E
#31
1$
1'
#32
0*
0'
#33
0$
1'
#34
1*
0'
#35
1$
1'
#36
0*
0'
#37
0$
1'
#38
1*
0'
#39
1$
1'
#40
0*
0'
#41
1'
#42
1*
0'
#43
0$
1'
#44
0*
0'
#45
1$
1'
#46
1*
0'
#47
0$
1'
#48
0*
0'
#49
1'
#50
1*
0'
#51
1'
#52
0*
0'
#53
1$
1'
#54
1*
0'
#55
0$
1'
#56
0*
0'
#57
1$
1'
#58
1*
0'
#59
1'
#60
0*
0'
#61
1'
#62
1*
0'
#63
1'
#64
0*
0'
#65
0$
1'
#66
1*
0'
#67
1'
#68
0*
0'
#69
1'
#70
1*
0'
#71
1'
#72
0*
0'
#73
1$
1'
#74
1*
0'
#75
0$
1'
#76
0*
0'
#77
1$
1'
#78
1*
0'
#79
1'
#80
0*
0'
#81
1'
#82
1*
0'
#83
1'
#84
1%
0*
0'
b01 N
b000000001 Q
b000000001 P
#85
1'
b01 M
1K
1:
b000000001 O
b00000001 3
b000000001 L
b000000001 5
b000000010 Q
b000000011 P
#86
1*
0'
#87
0$
1'
b000000001 ?
b000000010 O
b00000010 3
b000000011 L
b000000011 5
b000000011 Q
b000000010 P
#88
0*
0'
#89
1'
b000000011 ?
b000000001 >
b000000001 8
b000000011 O
b00000011 3
b000000010 L
b000000010 5
0J
b000000100 Q
b000000110 P
#90
1*
0'
0#
#91
1$
1'
b000000010 ?
b000000011 >
b000000011 8
b000000100 O
b00000100 3
b000000110 L
b000000110 5
b000000101 Q
b000000111 P
#92
0*
0'
#93
1'
b000000110 ?
b000000010 >
b000000010 8
b000000101 O
b00000101 3
b000000111 L
b000000111 5
b000000110 Q
b000000101 P
#94
1*
0'
#95
1'
b000000111 ?
b000000110 >
b000000110 8
b000000110 O
b00000110 3
b000000101 L
b000000101 5
b000000111 Q
b000000100 P
#96
0*
0'
#97
0$
1'
b000000101 ?
b000000111 >
b000000111 8
b000000111 O
b00000111 3
b000000100 L
b000000100 5
b000001000 Q
b000001100 P
#98
1*
0'
#99
1'
b000000100 ?
b000000101 >
b000000101 8
b000001000 O
b00001000 3
b000001100 L
b000001100 5
b000001001 Q
b000001101 P
#100
0*
0'
#101
1'
b000001100 ?
b000000100 >
b000000100 8
b000001001 O
b00001001 3
b000001101 L
b000001101 5
b000001010 Q
b000001111 P
#102
1*
0'
#103
1'
b000001101 ?
b000001100 >
b000001100 8
b000001010 O
b00001010 3
b000001111 L
b000001111 5
b000001011 Q
b000001110 P
#104
0*
0'
#105
1'
b000001111 ?
b000001101 >
b000001101 8
b000001011 O
b00001011 3
b000001110 L
b000001110 5
b000001100 Q
b000001010 P
#106
1*
0'
#107
1$
1'
b000001110 ?
b000001111 >
b000001111 8
b000001100 O
b00001100 3
b000001010 L
b000001010 5
b000001101 Q
b000001011 P
#108
0*
0'
#109
0$
1'
b000001010 ?
b000001110 >
b000001110 8
b000001101 O
b00001101 3
b000001011 L
b000001011 5
b000001110 Q
b000001001 P
#110
1*
0'
#111
1'
b000001011 ?
b000001010 >
b000001010 8
b000001110 O
b00001110 3
b000001001 L
b000001001 5
b000001111 Q
b000001000 P
#112
0*
0'
#113
1$
1'
b000001001 ?
b000001011 >
b000001011 8
b000001111 O
b00001111 3
b000001000 L
b000001000 5
b000010000 Q
b000011000 P
#114
1*
0'
#115
1'
b000001000 ?
b000001001 >
b000001001 8
b000010000 O
b00010000 3
b000011000 L
b000011000 5
b000010001 Q
b000011001 P
#116
0*
0'
#117
0$
1'
b000011000 ?
b000001000 >
b000001000 8
b000010001 O
b00010001 3
b000011001 L
b000011001 5
b000010010 Q
b000011011 P
#118
1*
0'
#119
1'
b000011001 ?
b000011000 >
b000011000 8
b000010010 O
b00010010 3
b000011011 L
b000011011 5
b000010011 Q
b000011010 P
#120
0*
0'
#121
1'
b000011011 ?
b000011001 >
b000011001 8
b000010011 O
b00010011 3
b000011010 L
b000011010 5
b000010100 Q
b000011110 P
#122
1*
0'
#123
1'
b000011010 ?
b000011011 >
b000011011 8
b000010100 O
b00010100 3
b000011110 L
b000011110 5
b000010101 Q
b000011111 P
#124
0*
0'
#125
1'
b000011110 ?
b000011010 >
b000011010 8
b000010101 O
b00010101 3
b000011111 L
b000011111 5
b000010110 Q
b000011101 P
#126
1*
0'
#127
1$
1'
b000011111 ?
b000011110 >
b000011110 8
b000010110 O
b00010110 3
b000011101 L
b000011101 5
b000010111 Q
b000011100 P
#128
0*
0'
#129
1'
b000011101 ?
b000011111 >
b000011111 8
b000010111 O
b00010111 3
b000011100 L
b000011100 5
b000011000 Q
b000010100 P
#130
1*
0'
#131
1'
b000011100 ?
b000011101 >
b000011101 8
b000011000 O
b00011000 3
b000010100 L
b000010100 5
b000011001 Q
b000010101 P
#132
0*
0'
#133
1'
b000010100 ?
b000011100 >
b000011100 8
b000011001 O
b00011001 3
b000010101 L
b000010101 5
b000011010 Q
b000010111 P
#134
0%
1*
0'
b10 N
b000011001 Q
b000010101 P
#135
1'
b000010101 ?
b000010100 >
b000010100 8
b10 M
0K
0:
#136
0*
0'
#137
0$
1'
b000010101 >
b000010101 8
#138
1*
0'
#139
1'
#140
0*
0'
#141
1$
1'
#142
1*
0'
#143
1'
#144
1)
0*
0'
b01 F
b000000001 I
b000000001 H
#145
1'
#146
1*
0'
b01 E
1C
1;
b000000001 G
b00000001 4
b000000001 D
b000000001 6
b000000010 I
b000000010 H
b000000011 H
#147
0$
1'
#148
0*
0'
#149
1'
#150
1*
0'
b000000001 =
b000000010 G
b00000010 4
b000000011 D
b000000011 6
b000000011 I
b000000010 H
#151
1$
1'
#152
0*
0'
#153
1'
#154
1*
0'
b000000011 =
b000000001 <
b000000001 7
b000000011 G
b00000011 4
b000000010 D
b000000010 6
b000000100 I
b000000101 H
b000000110 H
#155
0$
1'
#156
0*
0'
#157
1$
1'
#158
1*
0'
b000000010 =
b000000011 <
b000000011 7
1!
b000000100 G
b00000100 4
b000000110 D
b000000110 6
b000000101 I
b000000111 H
#159
1'
#160
0*
0'
#161
0$
1'
#162
1*
0'
b000000110 =
b000000010 <
b000000010 7
b000000101 G
b00000101 4
b000000111 D
b000000111 6
b000000110 I
b000000100 H
b000000101 H
#163
1$
1'
#164
0*
0'
#165
1'
#166
1*
0'
b000000111 =
b000000110 <
b000000110 7
b000000110 G
b00000110 4
b000000101 D
b000000101 6
b000000111 I
b000000100 H
#167
1'
#168
0*
0'
#169
0$
1'
#170
1*
0'
b000000101 =
b000000111 <
b000000111 7
0!
b000000111 G
b00000111 4
b000000100 D
b000000100 6
b000001000 I
b000001011 H
b000001100 H
#171
1$
1'
#172
0*
0'
#173
1'
#174
1*
0'
b000000100 =
b000000101 <
b000000101 7
b000001000 G
b00001000 4
b000001100 D
b000001100 6
b000001001 I
b000001101 H
#175
0$
1'
#176
0*
0'
#177
1'
#178
1*
0'
b000001100 =
b000000100 <
b000000100 7
b000001001 G
b00001001 4
b000001101 D
b000001101 6
b000001010 I
b000001110 H
b000001111 H
#179
1'
#180
0*
0'
#181
1'
#182
1*
0'
b000001101 =
b000001100 <
b000001100 7
b000001010 G
b00001010 4
b000001111 D
b000001111 6
b000001011 I
b000001110 H
#183
1$
1'
#184
0*
0'
#185
1'
#186
1*
0'
b000001111 =
b000001101 <
b000001101 7
b000001011 G
b00001011 4
b000001110 D
b000001110 6
b000001100 I
b000001001 H
b000001010 H
#187
0$
1'
#188
0*
0'
#189
1'
#190
1*
0'
b000001110 =
b000001111 <
b000001111 7
1!
b000001100 G
b00001100 4
b000001010 D
b000001010 6
b000001101 I
b000001011 H
#191
1$
1'
#192
0*
0'
#193
1'
#194
1*
0'
b000001010 =
b000001110 <
b000001110 7
0!
b000001101 G
b00001101 4
b000001011 D
b000001011 6
b000001110 I
b000001000 H
b000001001 H
#195
1'
#196
0*
0'
#197
1'
#198
1*
0'
b000001011 =
b000001010 <
b000001010 7
b000001110 G
b00001110 4
b000001001 D
b000001001 6
b000001111 I
b000001000 H
#199
1'
#200
0*
0'
#201
0$
1'
#202
1*
0'
b000001001 =
b000001011 <
b000001011 7
1!
b000001111 G
b00001111 4
b000001000 D
b000001000 6
b000010000 I
b000010111 H
b000011000 H
#203
1$
1'
#204
0*
0'
#205
1'
#206
1*
0'
b000001000 =
b000001001 <
b000001001 7
b000010000 G
b00010000 4
b000011000 D
b000011000 6
b000010001 I
b000011001 H
#207
1'
#208
0*
0'
#209
0$
1'
#210
1*
0'
b000011000 =
b000001000 <
b000001000 7
0!
b000010001 G
b00010001 4
b000011001 D
b000011001 6
b000010010 I
b000011010 H
b000011011 H
#211
1'
#212
0*
0'
#213
1'
#214
1*
0'
b000011001 =
b000011000 <
b000011000 7
b000010010 G
b00010010 4
b000011011 D
b000011011 6
b000010011 I
b000011010 H
#215
1'
#216
0*
0'
#217
1'
#218
1*
0'
b000011011 =
b000011001 <
b000011001 7
b000010011 G
b00010011 4
b000011010 D
b000011010 6
b000010100 I
b000011101 H
b000011110 H
#219
1'
#220
0*
0'
#221
1'
#222
1*
0'
b000011010 =
b000011011 <
b000011011 7
b000010100 G
b00010100 4
b000011110 D
b000011110 6
b000010101 I
b000011111 H
#223
1$
1'
#224
0*
0'
#225
1'
#226
1*
0'
b000011110 =
b000011010 <
b000011010 7
b000010101 G
b00010101 4
b000011111 D
b000011111 6
b000010110 I
b000011100 H
b000011101 H
#227
1'
#228
0*
0'
#229
1'
#230
1*
0'
b000011111 =
b000011110 <
b000011110 7
1!
b000010110 G
b00010110 4
b000011101 D
b000011101 6
b000010111 I
b000011100 H
#231
1'
#232
0*
0'
#233
0$
1'
#234
1*
0'
b000011101 =
b000011111 <
b000011111 7
b000010111 G
b00010111 4
b000011100 D
b000011100 6
b000011000 I
b000010011 H
b000010100 H
#235
1$
1'
#236
0*
0'
#237
1'
#238
1*
0'
b000011100 =
b000011101 <
b000011101 7
b000011000 G
b00011000 4
b000010100 D
b000010100 6
b000011001 I
b000010101 H
1J
#239
0$
1'
#240
0*
0'
#241
1'
#242
1*
0'
b000010100 =
b000011100 <
b000011100 7
1#
b000011001 G
b00011001 4
b000010101 D
b000010101 6
b10 F
b000011001 I
#243
1$
1'
#244
0)
1&
0*
0'
b00 N
#245
1'
b000000000 ?
b000000000 >
b000000000 8
1A
b00 M
b000000000 O
b00000000 3
b000000000 L
b000000000 5
0J
b000000000 Q
b000000000 P
#246
0&
1*
0'
b10 N
b000010101 =
b000010100 <
b000010100 7
0!
b10 E
0#
0C
0;
#247
0$
1'
0A
1@
19
b10 M
b00 F
#248
0*
0'
#249
1$
1'
0@
09
b10 F
#250
1*
0'
b000010101 <
b000010101 7
#251
1'
#252
0*
0'
#253
1'
#254
1*
0'
#255
1'
#256
0*
0'
#257
0$
1'
#258
1*
0'
#259
1'
#260
0*
0'
#261
1'
#262
1*
0'
#263
1$
1'
#264
0*
0'
#265
0$
1'
#266
1*
0'
#267
1'
#268
0*
0'
#269
1'
#270
1*
0'
#271
1$
1'
#272
0*
0'
#273
1'
#274
1*
0'
#275
0$
1'
#276
0*
0'
#277
1'
#278
1*
0'
#279
1$
1'
#280
0*
0'
#281
0$
1'
#282
1*
0'
#283
1'
#284
0*
0'
#285
1'
#286
1*
0'
#287
1$
1'
#288
0*
0'
#289
0$
1'
#290
1*
0'
#291
1'
#292
0*
0'
#293
1$
1'
#294
1*
0'
#295
0$
1'
#296
0*
0'
#297
1$
1'
