Serial Interface/serial_interface.sv
//Serial module for the Parallel Serial Interface
`timescale 1ns/1ps

`define SOF 8'h5a
`define EOF 8'h0f

module serial_interface
	#(parameter data_width = 5)
	(	input logic 	datain, s_clk, rst_n, req,
		output logic 	dataout, pop,
		output logic [1:0] state);

//==== SIGNALS ====
// input logic s_clk, rst_n;
// the data to be obtained from the FIFO
// input logic datain;

// when the FIFO wants output data (i.e. whenever it is not empty), this signal should be high
// when a frame is finished, the FIFO should set this signal low
// input logic req;

// that data to be sent out of the serial interface
// output logic dataout;

//when there is a successful data sample, this signal is sent high to tell the FIFO to pop the current data
//the serial interface expects new data on the next clock cycle
// output logic pop;

logic nextdataout, inputSample, request;
enum logic [1:0] {IDLE=2'b00, START_T=2'b01, DATA_T=2'b11, END_T=2'b10} state, nextstate;

logic [2:0] delimcounter, nextdelimcounter;
logic [data_width - 1:0] datacounter, nextdatacounter;

//==== FUNCTIONS ====
function findDelim;
  input startDelimeter;
  input [2:0] incount;

  //delimeters are read msb first, so inverted enumeration
  logic [0:7] delimToSend;

  begin: finddelim_def
    if(startDelimeter)
      delimToSend = `SOF;
    else
      delimToSend = `EOF;

    findDelim = delimToSend[incount];
  end: finddelim_def
endfunction: findDelim

//==== ALWAYS BLOCKS ====
always_ff @(posedge s_clk or negedge rst_n)
begin: updateff
  if(rst_n) begin
    state 		<= nextstate;
    delimcounter 	<= nextdelimcounter;
    dataout 		<= nextdataout;
    inputSample 	<= datain;
    request 		<= req;
    datacounter 	<= nextdatacounter;
  end
  else begin
    state 		<= IDLE;
    delimcounter 	<= 0;
    dataout 		<= 0;
    inputSample		<= 0;
    request 		<= 0;
    datacounter 	<= 0;
  end
end: updateff

always_comb
begin: statemachine
  case(state)
    IDLE: begin
      pop = 0;
      nextdatacounter = 0;
      if(request) 
	  begin
        nextstate = START_T;
        nextdelimcounter = 1;
        nextdataout = findDelim(1, delimcounter);
      end
      else
	  begin
        nextstate = IDLE;
        nextdelimcounter = 0;
        nextdataout = 0;
      end
    end

    START_T: begin
      nextdataout = findDelim(1, delimcounter);
      nextdatacounter = 0;
      if(delimcounter < 7) begin
        nextstate = START_T;
        nextdelimcounter = delimcounter + 1;
        if (delimcounter > 4)
          pop = 1;
        else
          pop = 0;
      end
      else begin
        nextstate = DATA_T;
        nextdelimcounter = 0;
        pop = 1;
      end
    end

    DATA_T: begin
      if(datacounter < (2 ** data_width) - 1 ) begin
        nextstate = DATA_T;
        nextdelimcounter = 0;
        nextdataout = inputSample;
        nextdatacounter = datacounter + 1;
        if (datacounter > (2 ** data_width) - 3)
          pop = 0;
        else
          pop = 1;
      end
      else begin
        nextstate = END_T;
        nextdelimcounter = 0;
        nextdataout =  inputSample;
        pop = 0;
        nextdatacounter = 0;
      end
    end

    END_T: begin
      pop = 0;
      nextdatacounter = 0;
      nextdataout = findDelim(0, delimcounter);
      if(delimcounter < 7) begin
        nextdelimcounter = delimcounter + 1;
        nextstate = END_T;
      end
      else begin
        nextdelimcounter = 0;
        nextstate = IDLE;
      end
    end
  endcase
end: statemachine

endmodule //end serial_interface

Serial Interface/serial_interface_tb.sv
//testbench for 'serial_psi.sv'
`timescale 1ns/1ps

module serial_interface_tb();
logic clk_tb, rst_tb_n, output_tb, input_tb, request_tb, pop_tb;
logic [1:0] state;

serial_interface dut1 (
  .s_clk(clk_tb),
  .rst_n(rst_tb_n),
  .dataout(output_tb),
  .datain(input_tb),
  .req(request_tb),
  .pop(pop_tb), 
  .state(state)
);

initial
begin: clock_setup
  clk_tb = 0;
  forever #5 clk_tb = !clk_tb;
end: clock_setup

initial
begin: device_testing
  rst_tb_n = 1; input_tb = 0; request_tb = 0;
  #13 rst_tb_n = 0;
  #20 rst_tb_n = 1;
  #20 input_tb = 1; request_tb = 1;
  #10 input_tb = 0;
  #40 input_tb = 1;
  #50 input_tb = 0;
  #10 input_tb = 1;
  #10 request_tb = 0;
  #400 $finish;
end: device_testing

initial
begin: dump_variables
  $dumpfile("serial_interface_vcd.vcd");
  $dumpvars();
end: dump_variables

endmodule

Serial Interface/serial_interface_vcd.vcd
$date
	Sun May  2 15:43:05 2021
$end

$version
	Synopsys VCS version I-2014.03-2
$end

$timescale
	1ps
$end

$comment Csum: 1 6d19fd2e610883d3 $end


$scope module serial_interface_tb $end
$var reg 1 ! clk_tb $end
$var reg 1 " rst_tb_n $end
$var reg 1 # output_tb $end
$var reg 1 $ input_tb $end
$var reg 1 % request_tb $end
$var reg 1 & pop_tb $end
$var reg 2 ' state [1:0] $end

$scope begin clock_setup $end
$upscope $end


$scope begin device_testing $end
$upscope $end


$scope begin dump_variables $end
$upscope $end


$scope module dut1 $end
$var reg 1 $ datain $end
$var reg 1 ! s_clk $end
$var reg 1 " rst_n $end
$var reg 1 % req $end
$var reg 1 # dataout $end
$var reg 1 & pop $end
$var reg 2 ' state [1:0] $end
$var reg 1 ( nextdataout $end
$var reg 1 ) inputSample $end
$var reg 1 * request $end
$var reg 2 + nextstate [1:0] $end
$var reg 3 , delimcounter [2:0] $end
$var reg 3 - nextdelimcounter [2:0] $end
$var reg 5 . datacounter [4:0] $end
$var reg 5 / nextdatacounter [4:0] $end

$scope function findDelim $end
$var reg 1 0 findDelim $end
$var reg 1 1 startDelimeter $end
$var reg 3 2 incount [2:0] $end
$var reg 8 3 delimToSend [0:7] $end

$scope begin finddelim_def $end
$upscope $end

$upscope $end


$scope begin updateff $end
$upscope $end


$scope begin statemachine $end
$upscope $end

$upscope $end

$upscope $end

$enddefinitions $end

#0
$dumpvars
0!
x0
x1
x)
0$
x(
x#
x&
x*
0%
1"
bxxxxx .
bxxx ,
bxxxxxxxx 3
bxxx 2
bxxxxx /
bxxx -
bxx +
bxx '
$end
#5000
1!
0)
0*
#10000
0!
#13000
0"
b00 '
b000 ,
0#
b00000 .
b00000 /
0&
0(
b000 -
b00 +
#15000
1!
#20000
0!
#25000
1!
#30000
0!
#33000
1"
#35000
1!
#40000
0!
#45000
1!
#50000
0!
#53000
1$
1%
#55000
1!
1)
1*
b001 -
b01 +
00
b01011010 3
b000 2
11
#60000
0!
#63000
0$
#65000
1!
b01 '
b001 ,
0)
1(
b010 -
10
b001 2
#70000
0!
#75000
1!
b010 ,
1#
0(
b011 -
00
b010 2
#80000
0!
#85000
1!
b011 ,
0#
1(
b100 -
10
b011 2
#90000
0!
#95000
1!
b100 ,
1#
b101 -
b100 2
#100000
0!
#103000
1$
#105000
1!
b101 ,
1)
0(
b110 -
1&
00
b101 2
#110000
0!
#115000
1!
b110 ,
0#
1(
b111 -
10
b110 2
#120000
0!
#125000
1!
b111 ,
1#
0(
b000 -
b11 +
00
b111 2
#130000
0!
#135000
1!
b11 '
b000 ,
0#
b00001 /
1(
#140000
0!
#145000
1!
1#
b00001 .
b00010 /
#150000
0!
#153000
0$
#155000
1!
0)
b00010 .
b00011 /
0(
#160000
0!
#163000
1$
#165000
1!
0#
1)
b00011 .
b00100 /
1(
#170000
0!
#173000
0%
#175000
1!
1#
0*
b00100 .
b00101 /
#180000
0!
#185000
1!
b00101 .
b00110 /
#190000
0!
#195000
1!
b00110 .
b00111 /
#200000
0!
#205000
1!
b00111 .
b01000 /
#210000
0!
#215000
1!
b01000 .
b01001 /
#220000
0!
#225000
1!
b01001 .
b01010 /
#230000
0!
#235000
1!
b01010 .
b01011 /
#240000
0!
#245000
1!
b01011 .
b01100 /
#250000
0!
#255000
1!
b01100 .
b01101 /
#260000
0!
#265000
1!
b01101 .
b01110 /
#270000
0!
#275000
1!
b01110 .
b01111 /
#280000
0!
#285000
1!
b01111 .
b10000 /
#290000
0!
#295000
1!
b10000 .
b10001 /
#300000
0!
#305000
1!
b10001 .
b10010 /
#310000
0!
#315000
1!
b10010 .
b10011 /
#320000
0!
#325000
1!
b10011 .
b10100 /
#330000
0!
#335000
1!
b10100 .
b10101 /
#340000
0!
#345000
1!
b10101 .
b10110 /
#350000
0!
#355000
1!
b10110 .
b10111 /
#360000
0!
#365000
1!
b10111 .
b11000 /
#370000
0!
#375000
1!
b11000 .
b11001 /
#380000
0!
#385000
1!
b11001 .
b11010 /
#390000
0!
#395000
1!
b11010 .
b11011 /
#400000
0!
#405000
1!
b11011 .
b11100 /
#410000
0!
#415000
1!
b11100 .
b11101 /
#420000
0!
#425000
1!
b11101 .
b11110 /
#430000
0!
#435000
1!
b11110 .
b11111 /
0&
#440000
0!
#445000
1!
b11111 .
b00000 /
b10 +
#450000
0!
#455000
1!
b10 '
b00000 .
0(
b001 -
b00001111 3
b000 2
01
#460000
0!
#465000
1!
b001 ,
0#
b010 -
b001 2
#470000
0!
#475000
1!
b010 ,
b011 -
b010 2
#480000
0!
#485000
1!
b011 ,
b100 -
b011 2
#490000
0!
#495000
1!
b100 ,
1(
b101 -
10
b100 2
#500000
0!
#505000
1!
b101 ,
1#
b110 -
b101 2
#510000
0!
#515000
1!
b110 ,
b111 -
b110 2
#520000
0!
#525000
1!
b111 ,
b00 +
b000 -
b111 2
#530000
0!
#535000
1!
b00 '
b000 ,
0(
#540000
0!
#545000
1!
0#
