Parallel Interface/parallel_interface.sv
`timescale 1ns/1ps
module parallel_interface (	input p_clk, input n_rst, input	logic req, 
							input	logic [31:0] parallel_data_in,
							output	logic  grant, 
							output	logic serial_data_out,
							output	logic out_data);

  	typedef enum {IDLE, TAKE_INPUT_DATA, SEND_SERIAL_OUTPUT} fsm;
    fsm cs, ns;
  
  	logic grant_temp, serial_data_out_temp;
  	int	  bit_counter_temp, bit_counter;
	logic [31:0] parallel_data_reg, parallel_data_reg_temp;
	logic out_data_temp ;
    //logic out_data = 0; 
  
  	assign serial_data_out = parallel_data_reg[0];
	assign out_data = out_data_temp;
    
	// current_state logic of FSM
	
  always_ff @(posedge p_clk, negedge n_rst) begin
        if(!n_rst) begin
            cs         			<=  IDLE;
            grant				<=	0;
            bit_counter			<= 0;
			parallel_data_reg	<= 0;
			//serial_data_out <= 0;
			//out_data_temp <= 0;
        end
        else begin
            cs          		<= ns;
          	grant				<= grant_temp;
            bit_counter 		<= bit_counter_temp;
            parallel_data_reg 	<= parallel_data_reg_temp;
			//serial_data_out <= serial_data_out_temp;
        end
	end
	
	// next_state and output logic of FSM
	
    always_comb begin
        case(cs)
            IDLE:	begin
              	//serial_data_out_temp = 0;
				bit_counter_temp 		= 0;
				parallel_data_reg_temp 	= 0;
				out_data_temp 			= 0;
              	if(req) begin
                	ns 			= TAKE_INPUT_DATA;
                	grant_temp 	= 1;
              	end
                else begin	
                  	ns 			= IDLE;
                  	grant_temp 	= 0;
                end
            end
          
            TAKE_INPUT_DATA:	begin
              	serial_data_out_temp 	= 0;
              	bit_counter_temp		= 0;
				parallel_data_reg_temp 	= parallel_data_in;
				out_data_temp 			= 1;
            	ns 						= SEND_SERIAL_OUTPUT;
				grant_temp 				= 1;
            end 
          
          SEND_SERIAL_OUTPUT:	begin
              bit_counter_temp 			= bit_counter + 1;         
              parallel_data_reg_temp 	= parallel_data_reg >> 1; 	//Loading the 32-bit parallel input data
              if(bit_counter <= 31 ) 
				ns = cs;
              else begin
                ns 					= IDLE;
				out_data_temp 		= 0;
				bit_counter_temp 	= 0;
				end
            end     
        endcase
    end      
endmodule

Parallel Interface/parallel_interface_tb.sv
`timescale 1ns/1ps
module parallel_interface_tb ();
		logic   p_clk; 
		logic   n_rst; 
		logic req; 
		logic [31:0] parallel_data_in; 
		wire  grant;
        	wire serial_data_out;
		wire out_data;
		
	parallel_interface p1(p_clk, n_rst, req, parallel_data_in, grant, serial_data_out, out_data);
  
	always #2 p_clk = ~p_clk;
	  
	initial 
	begin
		p_clk = 0;
		n_rst = 0;
		req = 0;
		parallel_data_in = 0;
		#5;
		n_rst = 1;
		#10;
		req = 1;
		#1;
		parallel_data_in = 32'h1111_1111;
		#75;
		req = 0;
		#10;
		req = 1;
		#1;
		parallel_data_in = 32'hffff_ffff;
		#75;
		req = 0;
		#150;
		$finish;
	  end
	  
	  initial begin
		$dumpfile("parallel_interface_vcd.vcd");
		$dumpvars();
	  end
	  
endmodule

Parallel Interface/parallel_interface_vcd.vcd
$date
	Sun May  2 10:21:50 2021
$end

$version
	Synopsys VCS version I-2014.03-2
$end

$timescale
	1ps
$end

$comment Csum: 1 9a000a6270c0ed65 $end


$scope module parallel_interface_tb $end
$var reg 1 ! p_clk $end
$var reg 1 " n_rst $end
$var reg 1 # req $end
$var reg 32 $ parallel_data_in [31:0] $end
$var wire 1 % grant $end
$var wire 1 & serial_data_out $end
$var wire 1 ' out_data $end

$scope module p1 $end
$var wire 1 ! p_clk $end
$var wire 1 " n_rst $end
$var reg 1 # req $end
$var reg 32 $ parallel_data_in [31:0] $end
$var reg 1 % grant $end
$var reg 1 & serial_data_out $end
$var reg 1 ' out_data $end
$var reg 32 ( cs [31:0] $end
$var reg 32 ) ns [31:0] $end
$var reg 1 * grant_temp $end
$var reg 1 + serial_data_out_temp $end
$var reg 32 , bit_counter_temp [31:0] $end
$var reg 32 - bit_counter [31:0] $end
$var reg 32 . parallel_data_reg [31:0] $end
$var reg 32 / parallel_data_reg_temp [31:0] $end
$var reg 1 0 out_data_temp $end
$upscope $end

$upscope $end

$enddefinitions $end

#0
$dumpvars
0*
0"
00
0%
0'
0&
0!
0#
x+
b00000000000000000000000000000000 $
b00000000000000000000000000000000 .
b00000000000000000000000000000000 /
b00000000000000000000000000000000 -
b00000000000000000000000000000000 ,
b00000000000000000000000000000000 (
b00000000000000000000000000000000 )
$end
#2000
1!
#4000
0!
#5000
1"
#6000
1!
#8000
0!
#10000
1!
#12000
0!
#14000
1!
#15000
1#
1*
b00000000000000000000000000000001 )
#16000
0!
b00010001000100010001000100010001 $
#18000
1!
b00000000000000000000000000000001 (
1%
b00000000000000000000000000000010 )
10
1'
b00010001000100010001000100010001 /
0+
#20000
0!
#22000
1!
b00000000000000000000000000000010 (
b00010001000100010001000100010001 .
1&
b00001000100010001000100010001000 /
b00000000000000000000000000000001 ,
#24000
0!
#26000
1!
b00000000000000000000000000000001 -
b00001000100010001000100010001000 .
0&
b00000100010001000100010001000100 /
b00000000000000000000000000000010 ,
#28000
0!
#30000
1!
b00000000000000000000000000000010 -
b00000100010001000100010001000100 .
b00000010001000100010001000100010 /
b00000000000000000000000000000011 ,
#32000
0!
#34000
1!
b00000000000000000000000000000011 -
b00000010001000100010001000100010 .
b00000001000100010001000100010001 /
b00000000000000000000000000000100 ,
#36000
0!
#38000
1!
b00000000000000000000000000000100 -
b00000001000100010001000100010001 .
1&
b00000000100010001000100010001000 /
b00000000000000000000000000000101 ,
#40000
0!
#42000
1!
b00000000000000000000000000000101 -
b00000000100010001000100010001000 .
0&
b00000000010001000100010001000100 /
b00000000000000000000000000000110 ,
#44000
0!
#46000
1!
b00000000000000000000000000000110 -
b00000000010001000100010001000100 .
b00000000001000100010001000100010 /
b00000000000000000000000000000111 ,
#48000
0!
#50000
1!
b00000000000000000000000000000111 -
b00000000001000100010001000100010 .
b00000000000100010001000100010001 /
b00000000000000000000000000001000 ,
#52000
0!
#54000
1!
b00000000000000000000000000001000 -
b00000000000100010001000100010001 .
1&
b00000000000010001000100010001000 /
b00000000000000000000000000001001 ,
#56000
0!
#58000
1!
b00000000000000000000000000001001 -
b00000000000010001000100010001000 .
0&
b00000000000001000100010001000100 /
b00000000000000000000000000001010 ,
#60000
0!
#62000
1!
b00000000000000000000000000001010 -
b00000000000001000100010001000100 .
b00000000000000100010001000100010 /
b00000000000000000000000000001011 ,
#64000
0!
#66000
1!
b00000000000000000000000000001011 -
b00000000000000100010001000100010 .
b00000000000000010001000100010001 /
b00000000000000000000000000001100 ,
#68000
0!
#70000
1!
b00000000000000000000000000001100 -
b00000000000000010001000100010001 .
1&
b00000000000000001000100010001000 /
b00000000000000000000000000001101 ,
#72000
0!
#74000
1!
b00000000000000000000000000001101 -
b00000000000000001000100010001000 .
0&
b00000000000000000100010001000100 /
b00000000000000000000000000001110 ,
#76000
0!
#78000
1!
b00000000000000000000000000001110 -
b00000000000000000100010001000100 .
b00000000000000000010001000100010 /
b00000000000000000000000000001111 ,
#80000
0!
#82000
1!
b00000000000000000000000000001111 -
b00000000000000000010001000100010 .
b00000000000000000001000100010001 /
b00000000000000000000000000010000 ,
#84000
0!
#86000
1!
b00000000000000000000000000010000 -
b00000000000000000001000100010001 .
1&
b00000000000000000000100010001000 /
b00000000000000000000000000010001 ,
#88000
0!
#90000
1!
b00000000000000000000000000010001 -
b00000000000000000000100010001000 .
0&
b00000000000000000000010001000100 /
b00000000000000000000000000010010 ,
#91000
0#
#92000
0!
#94000
1!
b00000000000000000000000000010010 -
b00000000000000000000010001000100 .
b00000000000000000000001000100010 /
b00000000000000000000000000010011 ,
#96000
0!
#98000
1!
b00000000000000000000000000010011 -
b00000000000000000000001000100010 .
b00000000000000000000000100010001 /
b00000000000000000000000000010100 ,
#100000
0!
#101000
1#
#102000
1!
b11111111111111111111111111111111 $
b00000000000000000000000000010100 -
b00000000000000000000000100010001 .
1&
b00000000000000000000000010001000 /
b00000000000000000000000000010101 ,
#104000
0!
#106000
1!
b00000000000000000000000000010101 -
b00000000000000000000000010001000 .
0&
b00000000000000000000000001000100 /
b00000000000000000000000000010110 ,
#108000
0!
#110000
1!
b00000000000000000000000000010110 -
b00000000000000000000000001000100 .
b00000000000000000000000000100010 /
b00000000000000000000000000010111 ,
#112000
0!
#114000
1!
b00000000000000000000000000010111 -
b00000000000000000000000000100010 .
b00000000000000000000000000010001 /
b00000000000000000000000000011000 ,
#116000
0!
#118000
1!
b00000000000000000000000000011000 -
b00000000000000000000000000010001 .
1&
b00000000000000000000000000001000 /
b00000000000000000000000000011001 ,
#120000
0!
#122000
1!
b00000000000000000000000000011001 -
b00000000000000000000000000001000 .
0&
b00000000000000000000000000000100 /
b00000000000000000000000000011010 ,
#124000
0!
#126000
1!
b00000000000000000000000000011010 -
b00000000000000000000000000000100 .
b00000000000000000000000000000010 /
b00000000000000000000000000011011 ,
#128000
0!
#130000
1!
b00000000000000000000000000011011 -
b00000000000000000000000000000010 .
b00000000000000000000000000000001 /
b00000000000000000000000000011100 ,
#132000
0!
#134000
1!
b00000000000000000000000000011100 -
b00000000000000000000000000000001 .
1&
b00000000000000000000000000000000 /
b00000000000000000000000000011101 ,
#136000
0!
#138000
1!
b00000000000000000000000000011101 -
b00000000000000000000000000000000 .
0&
b00000000000000000000000000011110 ,
#140000
0!
#142000
1!
b00000000000000000000000000011110 -
b00000000000000000000000000011111 ,
#144000
0!
#146000
1!
b00000000000000000000000000011111 -
b00000000000000000000000000100000 ,
#148000
0!
#150000
1!
b00000000000000000000000000100000 -
b00000000000000000000000000000000 ,
00
0'
b00000000000000000000000000000000 )
#152000
0!
#154000
1!
b00000000000000000000000000000000 (
b00000000000000000000000000000000 -
b00000000000000000000000000000001 )
#156000
0!
#158000
1!
b00000000000000000000000000000001 (
b00000000000000000000000000000010 )
10
1'
b11111111111111111111111111111111 /
#160000
0!
#162000
1!
b00000000000000000000000000000010 (
b11111111111111111111111111111111 .
1&
b01111111111111111111111111111111 /
b00000000000000000000000000000001 ,
#164000
0!
#166000
1!
b00000000000000000000000000000001 -
b01111111111111111111111111111111 .
b00111111111111111111111111111111 /
b00000000000000000000000000000010 ,
#168000
0!
#170000
1!
b00000000000000000000000000000010 -
b00111111111111111111111111111111 .
b00011111111111111111111111111111 /
b00000000000000000000000000000011 ,
#172000
0!
#174000
1!
b00000000000000000000000000000011 -
b00011111111111111111111111111111 .
b00001111111111111111111111111111 /
b00000000000000000000000000000100 ,
#176000
0!
#177000
0#
#178000
1!
b00000000000000000000000000000100 -
b00001111111111111111111111111111 .
b00000111111111111111111111111111 /
b00000000000000000000000000000101 ,
#180000
0!
#182000
1!
b00000000000000000000000000000101 -
b00000111111111111111111111111111 .
b00000011111111111111111111111111 /
b00000000000000000000000000000110 ,
#184000
0!
#186000
1!
b00000000000000000000000000000110 -
b00000011111111111111111111111111 .
b00000001111111111111111111111111 /
b00000000000000000000000000000111 ,
#188000
0!
#190000
1!
b00000000000000000000000000000111 -
b00000001111111111111111111111111 .
b00000000111111111111111111111111 /
b00000000000000000000000000001000 ,
#192000
0!
#194000
1!
b00000000000000000000000000001000 -
b00000000111111111111111111111111 .
b00000000011111111111111111111111 /
b00000000000000000000000000001001 ,
#196000
0!
#198000
1!
b00000000000000000000000000001001 -
b00000000011111111111111111111111 .
b00000000001111111111111111111111 /
b00000000000000000000000000001010 ,
#200000
0!
#202000
1!
b00000000000000000000000000001010 -
b00000000001111111111111111111111 .
b00000000000111111111111111111111 /
b00000000000000000000000000001011 ,
#204000
0!
#206000
1!
b00000000000000000000000000001011 -
b00000000000111111111111111111111 .
b00000000000011111111111111111111 /
b00000000000000000000000000001100 ,
#208000
0!
#210000
1!
b00000000000000000000000000001100 -
b00000000000011111111111111111111 .
b00000000000001111111111111111111 /
b00000000000000000000000000001101 ,
#212000
0!
#214000
1!
b00000000000000000000000000001101 -
b00000000000001111111111111111111 .
b00000000000000111111111111111111 /
b00000000000000000000000000001110 ,
#216000
0!
#218000
1!
b00000000000000000000000000001110 -
b00000000000000111111111111111111 .
b00000000000000011111111111111111 /
b00000000000000000000000000001111 ,
#220000
0!
#222000
1!
b00000000000000000000000000001111 -
b00000000000000011111111111111111 .
b00000000000000001111111111111111 /
b00000000000000000000000000010000 ,
#224000
0!
#226000
1!
b00000000000000000000000000010000 -
b00000000000000001111111111111111 .
b00000000000000000111111111111111 /
b00000000000000000000000000010001 ,
#228000
0!
#230000
1!
b00000000000000000000000000010001 -
b00000000000000000111111111111111 .
b00000000000000000011111111111111 /
b00000000000000000000000000010010 ,
#232000
0!
#234000
1!
b00000000000000000000000000010010 -
b00000000000000000011111111111111 .
b00000000000000000001111111111111 /
b00000000000000000000000000010011 ,
#236000
0!
#238000
1!
b00000000000000000000000000010011 -
b00000000000000000001111111111111 .
b00000000000000000000111111111111 /
b00000000000000000000000000010100 ,
#240000
0!
#242000
1!
b00000000000000000000000000010100 -
b00000000000000000000111111111111 .
b00000000000000000000011111111111 /
b00000000000000000000000000010101 ,
#244000
0!
#246000
1!
b00000000000000000000000000010101 -
b00000000000000000000011111111111 .
b00000000000000000000001111111111 /
b00000000000000000000000000010110 ,
#248000
0!
#250000
1!
b00000000000000000000000000010110 -
b00000000000000000000001111111111 .
b00000000000000000000000111111111 /
b00000000000000000000000000010111 ,
#252000
0!
#254000
1!
b00000000000000000000000000010111 -
b00000000000000000000000111111111 .
b00000000000000000000000011111111 /
b00000000000000000000000000011000 ,
#256000
0!
#258000
1!
b00000000000000000000000000011000 -
b00000000000000000000000011111111 .
b00000000000000000000000001111111 /
b00000000000000000000000000011001 ,
#260000
0!
#262000
1!
b00000000000000000000000000011001 -
b00000000000000000000000001111111 .
b00000000000000000000000000111111 /
b00000000000000000000000000011010 ,
#264000
0!
#266000
1!
b00000000000000000000000000011010 -
b00000000000000000000000000111111 .
b00000000000000000000000000011111 /
b00000000000000000000000000011011 ,
#268000
0!
#270000
1!
b00000000000000000000000000011011 -
b00000000000000000000000000011111 .
b00000000000000000000000000001111 /
b00000000000000000000000000011100 ,
#272000
0!
#274000
1!
b00000000000000000000000000011100 -
b00000000000000000000000000001111 .
b00000000000000000000000000000111 /
b00000000000000000000000000011101 ,
#276000
0!
#278000
1!
b00000000000000000000000000011101 -
b00000000000000000000000000000111 .
b00000000000000000000000000000011 /
b00000000000000000000000000011110 ,
#280000
0!
#282000
1!
b00000000000000000000000000011110 -
b00000000000000000000000000000011 .
b00000000000000000000000000000001 /
b00000000000000000000000000011111 ,
#284000
0!
#286000
1!
b00000000000000000000000000011111 -
b00000000000000000000000000000001 .
b00000000000000000000000000000000 /
b00000000000000000000000000100000 ,
#288000
0!
#290000
1!
b00000000000000000000000000100000 -
b00000000000000000000000000000000 .
0&
b00000000000000000000000000000000 ,
00
0'
b00000000000000000000000000000000 )
#292000
0!
#294000
1!
b00000000000000000000000000000000 (
b00000000000000000000000000000000 -
0*
#296000
0!
#298000
1!
0%
